brealid/__init__.py
brealid/ctf/__init__.py
brealid/ctf/crypto/EasyCrypt.py
brealid/ctf/crypto/GaloisNumber_2n.py
brealid/ctf/crypto/__init__.py
brealid/utils/__init__.py
brealid/utils/benchmark.py
brealid/utils/calc.py
brealid-0.0.10.dist-info/LICENSE
brealid-0.0.10.dist-info/METADATA
brealid-0.0.10.dist-info/WHEEL
brealid-0.0.10.dist-info/top_level.txt
brealid-0.0.10.dist-info/RECORD
