Metadata-Version: 2.1
Name: brealid
Version: 0.0.10
Summary: brealid's python package
Home-page: https://github.com/brealid/brealid-python-lib
Author: brealid
Author-email: brealid@mail.ustc.edu.cn
Classifier: Programming Language :: Python :: 3
Classifier: License :: OSI Approved :: MIT License
Classifier: Operating System :: OS Independent
Requires-Python: >=3.6
License-File: LICENSE
Requires-Dist: pycryptodome >=3.15.0
Requires-Dist: requests >=2.24.0
Requires-Dist: tqdm >=4.0.0
